odoo/addons/spreadsheet_dashboard_purchase_stock_oca/README.rst
odoo/addons/spreadsheet_dashboard_purchase_stock_oca/__init__.py
odoo/addons/spreadsheet_dashboard_purchase_stock_oca/__manifest__.py
odoo/addons/spreadsheet_dashboard_purchase_stock_oca/data/dashboards.xml
odoo/addons/spreadsheet_dashboard_purchase_stock_oca/data/files/purchase_dashboard.json
odoo/addons/spreadsheet_dashboard_purchase_stock_oca/i18n/ar.po
odoo/addons/spreadsheet_dashboard_purchase_stock_oca/i18n/az.po
odoo/addons/spreadsheet_dashboard_purchase_stock_oca/i18n/bg.po
odoo/addons/spreadsheet_dashboard_purchase_stock_oca/i18n/ca.po
odoo/addons/spreadsheet_dashboard_purchase_stock_oca/i18n/cs.po
odoo/addons/spreadsheet_dashboard_purchase_stock_oca/i18n/da.po
odoo/addons/spreadsheet_dashboard_purchase_stock_oca/i18n/de.po
odoo/addons/spreadsheet_dashboard_purchase_stock_oca/i18n/el.po
odoo/addons/spreadsheet_dashboard_purchase_stock_oca/i18n/es.po
odoo/addons/spreadsheet_dashboard_purchase_stock_oca/i18n/es_419.po
odoo/addons/spreadsheet_dashboard_purchase_stock_oca/i18n/es_CL.po
odoo/addons/spreadsheet_dashboard_purchase_stock_oca/i18n/et.po
odoo/addons/spreadsheet_dashboard_purchase_stock_oca/i18n/fa.po
odoo/addons/spreadsheet_dashboard_purchase_stock_oca/i18n/fi.po
odoo/addons/spreadsheet_dashboard_purchase_stock_oca/i18n/fr.po
odoo/addons/spreadsheet_dashboard_purchase_stock_oca/i18n/he.po
odoo/addons/spreadsheet_dashboard_purchase_stock_oca/i18n/hi.po
odoo/addons/spreadsheet_dashboard_purchase_stock_oca/i18n/hr.po
odoo/addons/spreadsheet_dashboard_purchase_stock_oca/i18n/hu.po
odoo/addons/spreadsheet_dashboard_purchase_stock_oca/i18n/hy.po
odoo/addons/spreadsheet_dashboard_purchase_stock_oca/i18n/id.po
odoo/addons/spreadsheet_dashboard_purchase_stock_oca/i18n/is.po
odoo/addons/spreadsheet_dashboard_purchase_stock_oca/i18n/it.po
odoo/addons/spreadsheet_dashboard_purchase_stock_oca/i18n/ja.po
odoo/addons/spreadsheet_dashboard_purchase_stock_oca/i18n/ko.po
odoo_addon_spreadsheet_dashboard_purchase_stock_oca-18.0.1.0.0.4.dist-info/METADATA
odoo_addon_spreadsheet_dashboard_purchase_stock_oca-18.0.1.0.0.4.dist-info/WHEEL
odoo_addon_spreadsheet_dashboard_purchase_stock_oca-18.0.1.0.0.4.dist-info/top_level.txt
odoo_addon_spreadsheet_dashboard_purchase_stock_oca-18.0.1.0.0.4.dist-info/RECORD
